pickuppath/__init__.py
pickuppath/__main__.py
pickuppath-0.1.1.dist-info/DESCRIPTION.rst
pickuppath-0.1.1.dist-info/entry_points.txt
pickuppath-0.1.1.dist-info/METADATA
pickuppath-0.1.1.dist-info/metadata.json
pickuppath-0.1.1.dist-info/RECORD
pickuppath-0.1.1.dist-info/top_level.txt
pickuppath-0.1.1.dist-info/WHEEL
