Metadata-Version: 2.0
Name: pickuppath
Version: 0.1.1
Summary: pickup path
Home-page: https://github.com/podhmo/pickuppath
Author: podhmo
Author-email: ababjam61+github@gmail.com
License: UNKNOWN
Platform: UNKNOWN
Classifier: Programming Language :: Python
Classifier: Programming Language :: Python :: Implementation :: CPython
Provides-Extra: docs
Provides-Extra: testing
